bp3/__init__.py
bp3/bepipred3.py
bp3/BP3Models/BP3C50IDFFNN/Fold1.pt
bp3/BP3Models/BP3C50IDFFNN/Fold2.pt
bp3/BP3Models/BP3C50IDFFNN/Fold3.pt
bp3/BP3Models/BP3C50IDFFNN/Fold4.pt
bp3/BP3Models/BP3C50IDFFNN/Fold5.pt
bp3/BP3Models/BP3C50IDSeqLenFFNN/Fold1.pt
bp3/BP3Models/BP3C50IDSeqLenFFNN/Fold2.pt
bp3/BP3Models/BP3C50IDSeqLenFFNN/Fold3.pt
bp3/BP3Models/BP3C50IDSeqLenFFNN/Fold4.pt
bp3/BP3Models/BP3C50IDSeqLenFFNN/Fold5.pt
bp3-0.0.12.5.dist-info/LICENSE
bp3-0.0.12.5.dist-info/METADATA
bp3-0.0.12.5.dist-info/WHEEL
bp3-0.0.12.5.dist-info/entry_points.txt
bp3-0.0.12.5.dist-info/top_level.txt
bp3-0.0.12.5.dist-info/RECORD
