Metadata-Version: 2.1
Name: bp3
Version: 0.0.12.5
Summary: Bepipred-3.0. B-cell epitope prediction
Home-page: https://github.com/UberClifford/BepiPred3.0-Predictor
Author: Joakim Clifford
Author-email: cliffordjoakim@gmail.com
Project-URL: Bug Tracker, https://github.com/UberClifford/BepiPred3.0-Predictor/issues
Classifier: Programming Language :: Python :: 3
Classifier: License :: OSI Approved :: MIT License
Classifier: Operating System :: OS Independent
License-File: LICENSE
Requires-Dist: setuptools
Requires-Dist: importlib-resources
